caribou/__init__.py
caribou/cli.py
caribou/migrate.py
caribou-0.4.1.dist-info/entry_points.txt
caribou-0.4.1.dist-info/WHEEL
caribou-0.4.1.dist-info/METADATA
caribou-0.4.1.dist-info/RECORD
