Metadata-Version: 2.1
Name: caribou
Version: 0.4.1
Summary: Caribou is a simple SQLite database migrations library, built
Author-email: Matt Perpick <clutchski@gmail.com>
Project-URL: Home, https://github.com/clutchski/caribou
